yunit/__init__.py
yunit/backwards_compatibility.py
yunit/matplotlib_support.py
yunit/prefixes.py
yunit/test.py
yunit/type_aliases.py
yunit/util.py
yunit/array/__init__.py
yunit/array/array.py
yunit/array/quantity.py
yunit/core_objects/_1_array.py
yunit/core_objects/_2_quantity.py
yunit/core_objects/_3_unit.py
yunit/core_objects/__init__.py
yunit/core_objects/ufunc.py
yunit/core_objects/unit_internals/_1_unit_atom.py
yunit/core_objects/unit_internals/_2_powered_unit_atom.py
yunit/core_objects/unit_internals/_3_compound_unit.py
yunit/core_objects/unit_internals/__init__.py
yunit/unit/_01_base_class.py
yunit/unit/_02_simple_unit.py
yunit/unit/_03_powered_unit.py
yunit/unit/_04_compound_unit.py
yunit/unit/__init__.py
yunit/unit/prefixes.py
yunit-0.2.dist-info/METADATA
yunit-0.2.dist-info/WHEEL
yunit-0.2.dist-info/top_level.txt
yunit-0.2.dist-info/RECORD
